Workbook

Sheet task-16
A3: Order ID | B3: Order Date | C3: Customer Name | D3: Product | E3: Category | F3: Region | G3: Quantity | H3: List Price | I3: Discount | J3: Unit Price | K3: Sales | L3: Cost | M3: Profit | N3: Salesperson | O3: Month | P3: Month Number | Q3: Profit Margin %
A4: ORD-1065 | B4: 46114.392 | C4: Nikhil Joshi | D4: Monitor | E4: Electronics | F4: East | G4: 4 | H4: 15000 | I4: 0.1 | J4: 13500 | K4: 54000 | L4: 37739.8 | M4: 16260.2 | N4: Diya | O4: Apr | P4: 4 | Q4: 0.30111481
A5: ORD-1103 | B5: 46116.58 | C5: Komal Shah | D5: Mouse | E5: Accessories | F5: West | G5: 5 | H5: 1200 | I5: 0.15 | J5: 1020 | K5: 5100 | L5: 3541.19 | M5: 1558.81 | N5: Meera | O5: Apr | P5: 4 | Q5: 0.30564902
A6: ORD-1113 | B6: 46118.46 | C6: Jay Joshi | D6: Laptop | E6: Electronics | F6: South | G6: 1 | H6: 55000 | I6: 0.05 | J6: 52250 | K6: 52250 | L6: 37092.49 | M6: 15157.51 | N6: Meera | O6: Apr | P6: 4 | Q6: 0.29009589
A7: ORD-1183 | B7: 46119.46 | C7: Vivek Shah | D7: Desk | E7: Furniture | F7: North | G7: 5 | H7: 12000 | I7: 0.05 | J7: 11400 | K7: 57000 | L7: 36885.94 | M7: 20114.06 | N7: Aarav | O7: Apr | P7: 4 | Q7: 0.35287825
A8: ORD-1112 | B8: 46119.836 | C8: Manav Patel | D8: Backpack | E8: Accessories | F8: South | G8: 4 | H8: 1800 | I8: 0 | J8: 1800 | K8: 7200 | L8: 5705.1 | M8: 1494.9 | N8: Meera | O8: Apr | P8: 4 | Q8: 0.207625
A9: ORD-1096 | B9: 46120.674 | C9: Yash Shah | D9: Keyboard | E9: Accessories | F9: North | G9: 1 | H9: 2200 | I9: 0 | J9: 2200 | K9: 2200 | L9: 1464.19 | M9: 735.81 | N9: Meera | O9: Apr | P9: 4 | Q9: 0.33445909
A10: ORD-1077 | B10: 46120.498 | C10: Meera Shah | D10: Desk | E10: Furniture | F10: South | G10: 2 | H10: 12000 | I10: 0 | J10: 12000 | K10: 24000 | L10: 16905.36 | M10: 7094.64 | N10: Aarav | O10: Apr | P10: 4 | Q10: 0.29561
A11: ORD-1165 | B11: 46121.667 | C11: Rohan Desai | D11: Printer | E11: Electronics | F11: North | G11: 4 | H11: 11000 | I11: 0.15 | J11: 9350 | K11: 37400 | L11: 27459.43 | M11: 9940.57 | N11: Kabir | O11: Apr | P11: 4 | Q11: 0.26579064
A12: ORD-1144 | B12: 46121.703 | C12: Rupal Joshi | D12: Mouse | E12: Accessories | F12: West | G12: 5 | H12: 1200 | I12: 0.05 | J12: 1140 | K12: 5700 | L12: 4553.41 | M12: 1146.59 | N12: Aarav | O12: Apr | P12: 4 | Q12: 0.20115614
A13: ORD-1203 | B13: 46122.62 | C13: Kavya Patel | D13: Printer | E13: Electronics | F13: South | G13: 5 | H13: 11000 | I13: 0.1 | J13: 9900 | K13: 49500 | L13: 33034.32 | M13: 16465.68 | N13: Diya | O13: Apr | P13: 4 | Q13: 0.33264
A14: ORD-1015 | B14: 46123.406 | C14: Smit Mehta | D14: Keyboard | E14: Accessories | F14: North | G14: 5 | H14: 2200 | I14: 0 | J14: 2200 | K14: 11000 | L14: 8101.6 | M14: 2898.4 | N14: Arjun | O14: Apr | P14: 4 | Q14: 0.26349091
A15: ORD-1066 | B15: 46123.47 | C15: Krish Joshi | D15: Backpack | E15: Accessories | F15: West | G15: 1 | H15: 1800 | I15: 0 | J15: 1800 | K15: 1800 | L15: 1426.86 | M15: 373.14 | N15: Riya | O15: Apr | P15: 4 | Q15: 0.2073
... A136: ORD-1109 | B136: 46171.647 | C136: Nirav Desai | D136: Backpack | E136: Accessories | F136: West | G136: 2 | H136: 1800 | I136: 0.1 | J136: 1620 | K136: 3240 | L136: 2439.97 | M136: 800.03 | N136: Arjun | O136: May | P136: 5 | Q136: 0.24692284

Sheet Profitability Analysis
A3: Metric | B3: Value
A4: Total Revenue | B4: =SUM('[1]task-16'!$K4:$K136) -> 4877250
A5: Total Cost | B5: =SUM('[1]task-16'!$L4:$L136) -> 3459709.7
A6: Total Discount | B6: =SUMPRODUCT('[1]task-16'!$H4:$H136,'[1]task-16'!$I4:$I136,'[1]task-16'!$G4:$G136) -> 294050
A7: Total Profit | B7: =SUM('[1]task-16'!$M4:$M136) -> 1417540.3
A8: Profit Margin % | B8: =IF(B4=0,0,B7/B4) -> 0.29064336
A9: Discount as % of Revenue | B9: =IF(B4=0,0,B6/B4) -> 0.060290123
A13: Category | B13: Revenue | C13: Cost | D13: Profit | E13: Profit Margin %
A14: Electronics | B14: =SUMIF('task-16'!$E4:$E136,A14,'task-16'!$K4:$K136) -> 4042950 | C14: =SUMIF('task-16'!$E4:$E136,A14,'task-16'!$L4:$L136) -> 2863859.9 | D14: =SUMIF('task-16'!$E4:$E136,A14,'task-16'!$M4:$M136) -> 1179090.1 | E14: =IF(B14=0,0,D14/B14) -> 0.29164103
A15: Accessories | B15: =SUMIF('task-16'!$E4:$E136,A15,'task-16'!$K4:$K136) -> 257150 | C15: =SUMIF('task-16'!$E4:$E136,A15,'task-16'!$L4:$L136) -> 184304.14 | D15: =SUMIF('task-16'!$E4:$E136,A15,'task-16'!$M4:$M136) -> 72845.86 | E15: =IF(B15=0,0,D15/B15) -> 0.28328159
A16: Furniture | B16: =SUMIF('task-16'!$E4:$E136,A16,'task-16'!$K4:$K136) -> 636250 | C16: =SUMIF('task-16'!$E4:$E136,A16,'task-16'!$L4:$L136) -> 452826.65 | D16: =SUMIF('task-16'!$E4:$E136,A16,'task-16'!$M4:$M136) -> 183423.35 | E16: =IF(B16=0,0,D16/B16) -> 0.28828817

Sheet Regional Profitability Analysis
A3: Region | B3: Revenue | C3: Cost | D3: Profit | E3: Profit Margin %
A4: East | B4: =SUMIF('task-16'!$F4:$F136,A4,'task-16'!$K4:$K136) -> 1353405 | C4: =SUMIF('task-16'!$F4:$F136,A4,'task-16'!$L4:$L136) -> 974433.57 | D4: =SUMIF('task-16'!$F4:$F136,A4,'task-16'!$M4:$M136) -> 378971.43 | E4: =IF(B4=0,0,D4/B4) -> 0.28001332
A5: West | B5: =SUMIF('task-16'!$F4:$F136,A5,'task-16'!$K4:$K136) -> 728850 | C5: =SUMIF('task-16'!$F4:$F136,A5,'task-16'!$L4:$L136) -> 535211.69 | D5: =SUMIF('task-16'!$F4:$F136,A5,'task-16'!$M4:$M136) -> 193638.31 | E5: =IF(B5=0,0,D5/B5) -> 0.26567649
A6: North | B6: =SUMIF('task-16'!$F4:$F136,A6,'task-16'!$K4:$K136) -> 1459310 | C6: =SUMIF('task-16'!$F4:$F136,A6,'task-16'!$L4:$L136) -> 1033812.2 | D6: =SUMIF('task-16'!$F4:$F136,A6,'task-16'!$M4:$M136) -> 425497.78 | E6: =IF(B6=0,0,D6/B6) -> 0.29157463
A7: South | B7: =SUMIF('task-16'!$F4:$F136,A7,'task-16'!$K4:$K136) -> 1394785 | C7: =SUMIF('task-16'!$F4:$F136,A7,'task-16'!$L4:$L136) -> 957533.19 | D7: =SUMIF('task-16'!$F4:$F136,A7,'task-16'!$M4:$M136) -> 437251.81 | E7: =IF(B7=0,0,D7/B7) -> 0.31349047

Sheet Product-level Profitability Ana
A3: Product | B3: Revenue | C3: Cost | D3: Profit | E3: Profit Margin %
A4: Laptop | B4: =SUMIF('task-16'!$D4:$D136,A4,'task-16'!$K4:$K136) -> 2315500 | C4: =SUMIF('task-16'!$D4:$D136,A4,'task-16'!$L4:$L136) -> 1624741.1 | D4: =SUMIF('task-16'!$D4:$D136,A4,'task-16'!$M4:$M136) -> 690758.94 | E4: =IF(B4=0,0,D4/B4) -> 0.29831956
A5: Smartphone | B5: =SUMIF('task-16'!$D4:$D136,A5,'task-16'!$K4:$K136) -> 603400 | C5: =SUMIF('task-16'!$D4:$D136,A5,'task-16'!$L4:$L136) -> 419617.08 | D5: =SUMIF('task-16'!$D4:$D136,A5,'task-16'!$M4:$M136) -> 183782.92 | E5: =IF(B5=0,0,D5/B5) -> 0.30457892
A6: Monitor | B6: =SUMIF('task-16'!$D4:$D136,A6,'task-16'!$K4:$K136) -> 625500 | C6: =SUMIF('task-16'!$D4:$D136,A6,'task-16'!$L4:$L136) -> 457926.84 | D6: =SUMIF('task-16'!$D4:$D136,A6,'task-16'!$M4:$M136) -> 167573.16 | E6: =IF(B6=0,0,D6/B6) -> 0.26790273
A7: Desk | B7: =SUMIF('task-16'!$D4:$D136,A7,'task-16'!$K4:$K136) -> 441600 | C7: =SUMIF('task-16'!$D4:$D136,A7,'task-16'!$L4:$L136) -> 308562.64 | D7: =SUMIF('task-16'!$D4:$D136,A7,'task-16'!$M4:$M136) -> 133037.36 | E7: =IF(B7=0,0,D7/B7) -> 0.30126214
A8: Printer | B8: =SUMIF('task-16'!$D4:$D136,A8,'task-16'!$K4:$K136) -> 392150 | C8: =SUMIF('task-16'!$D4:$D136,A8,'task-16'!$L4:$L136) -> 281398.54 | D8: =SUMIF('task-16'!$D4:$D136,A8,'task-16'!$M4:$M136) -> 110751.46 | E8: =IF(B8=0,0,D8/B8) -> 0.28242117
A9: Office Chair | B9: =SUMIF('task-16'!$D4:$D136,A9,'task-16'!$K4:$K136) -> 194650 | C9: =SUMIF('task-16'!$D4:$D136,A9,'task-16'!$L4:$L136) -> 144264.01 | D9: =SUMIF('task-16'!$D4:$D136,A9,'task-16'!$M4:$M136) -> 50385.99 | E9: =IF(B9=0,0,D9/B9) -> 0.2588543
A10: Backpack | B10: =SUMIF('task-16'!$D4:$D136,A10,'task-16'!$K4:$K136) -> 122130 | C10: =SUMIF('task-16'!$D4:$D136,A10,'task-16'!$L4:$L136) -> 88541.12 | D10: =SUMIF('task-16'!$D4:$D136,A10,'task-16'!$M4:$M136) -> 33588.88 | E10: =IF(B10=0,0,D10/B10) -> 0.27502563
A11: Headphones | B11: =SUMIF('task-16'!$D4:$D136,A11,'task-16'!$K4:$K136) -> 106400 | C11: =SUMIF('task-16'!$D4:$D136,A11,'task-16'!$L4:$L136) -> 80176.36 | D11: =SUMIF('task-16'!$D4:$D136,A11,'task-16'!$M4:$M136) -> 26223.64 | E11: =IF(B11=0,0,D11/B11) -> 0.24646278
A12: Keyboard | B12: =SUMIF('task-16'!$D4:$D136,A12,'task-16'!$K4:$K136) -> 82280 | C12: =SUMIF('task-16'!$D4:$D136,A12,'task-16'!$L4:$L136) -> 59296.51 | D12: =SUMIF('task-16'!$D4:$D136,A12,'task-16'!$M4:$M136) -> 22983.49 | E12: =IF(B12=0,0,D12/B12) -> 0.27933264
A13: Mouse | B13: =SUMIF('task-16'!$D4:$D136,A13,'task-16'!$K4:$K136) -> 52740 | C13: =SUMIF('task-16'!$D4:$D136,A13,'task-16'!$L4:$L136) -> 36466.51 | D13: =SUMIF('task-16'!$D4:$D136,A13,'task-16'!$M4:$M136) -> 16273.49 | E13: =IF(B13=0,0,D13/B13) -> 0.30856068

Sheet Shipping & Returns Analysis
B4: Metric | C4: Availability
B5: Shipping Cost | C5: Not Available
B6: Returns | C6: Not Available
B7: Return Cost/Impact | C7: Not Available
B9: Note : Shipping Cost and Returns data are not available in the source dataset.
