Workbook

Sheet Sales Data
A1: Order ID | B1: Order Date | C1: Customer Name | D1: Product | E1: Category | F1: Region | G1: Quantity | H1: List Price | I1: Discount | J1: Unit Price | K1: Sales | L1: Cost | M1: Profit | N1: Salesperson | O1: Month | P1: Month Number
A2: ORD-1083 | B2: 46025.797 | C2: Mansi Patel | D2: Headphones | E2: Electronics | F2: East | G2: 5 | H2: 3500 | I2: 0.05 | J2: 3325 | K2: 16625 | L2: 13379.28 | M2: 3245.72 | N2: Kabir | O2: Jan | P2: 1
A3: ORD-1238 | B3: 46025.604 | C3: Chirag Mehta | D3: Monitor | E3: Electronics | F3: East | G3: 2 | H3: 15000 | I3: 0.1 | J3: 13500 | K3: 27000 | L3: 20203.96 | M3: 6796.04 | N3: Riya | O3: Jan | P3: 1
A4: ORD-1198 | B4: 46027.509 | C4: Rohan Desai | D4: Office Chair | E4: Furniture | F4: West | G4: 2 | H4: 8500 | I4: 0.1 | J4: 7650 | K4: 15300 | L4: 10919.3 | M4: 4380.7 | N4: Aarav | O4: Jan | P4: 1
A5: ORD-1206 | B5: 46031.501 | C5: Anjali Desai | D5: Headphones | E5: Electronics | F5: West | G5: 3 | H5: 3500 | I5: 0.05 | J5: 3325 | K5: 9975 | L5: 6668.05 | M5: 3306.95 | N5: Diya | O5: Jan | P5: 1
A6: ORD-1079 | B6: 46032.779 | C6: Nirav Desai | D6: Monitor | E6: Electronics | F6: East | G6: 5 | H6: 15000 | I6: 0.1 | J6: 13500 | K6: 67500 | L6: 53215.05 | M6: 14284.95 | N6: Kabir | O6: Jan | P6: 1
A7: ORD-1159 | B7: 46033.513 | C7: Vivek Shah | D7: Laptop | E7: Electronics | F7: North | G7: 4 | H7: 55000 | I7: 0.1 | J7: 49500 | K7: 198000 | L7: 125651.85 | M7: 72348.15 | N7: Kabir | O7: Jan | P7: 1
A8: ORD-1154 | B8: 46036.633 | C8: Vishal Mehta | D8: Keyboard | E8: Accessories | F8: East | G8: 4 | H8: 2200 | I8: 0 | J8: 2200 | K8: 8800 | L8: 6999.67 | M8: 1800.33 | N8: Kabir | O8: Jan | P8: 1
A9: ORD-1128 | B9: 46038.526 | C9: Aditi Joshi | D9: Printer | E9: Electronics | F9: West | G9: 4 | H9: 11000 | I9: 0 | J9: 11000 | K9: 44000 | L9: 28778.61 | M9: 15221.39 | N9: Meera | O9: Jan | P9: 1
A10: ORD-1122 | B10: 46038.367 | C10: Hardik Patel | D10: Headphones | E10: Electronics | F10: North | G10: 5 | H10: 3500 | I10: 0.1 | J10: 3150 | K10: 15750 | L10: 11803.37 | M10: 3946.63 | N10: Aarav | O10: Jan | P10: 1
A11: ORD-1118 | B11: 46040.787 | C11: Anjali Desai | D11: Keyboard | E11: Accessories | F11: North | G11: 1 | H11: 2200 | I11: 0 | J11: 2200 | K11: 2200 | L11: 1743.54 | M11: 456.46 | N11: Meera | O11: Jan | P11: 1
A12: ORD-1181 | B12: 46040.662 | C12: Arjun Mehta | D12: Keyboard | E12: Accessories | F12: North | G12: 2 | H12: 2200 | I12: 0 | J12: 2200 | K12: 4400 | L12: 2867.57 | M12: 1532.43 | N12: Arjun | O12: Jan | P12: 1
A13: ORD-1201 | B13: 46041.624 | C13: Raj Desai | D13: Monitor | E13: Electronics | F13: West | G13: 5 | H13: 15000 | I13: 0 | J13: 15000 | K13: 75000 | L13: 50125.1 | M13: 24874.9 | N13: Aarav | O13: Jan | P13: 1
... A251: ORD-1134 | B251: 46294.715 | C251: Mitali Shah | D251: Monitor | E251: Electronics | F251: North | G251: 1 | H251: 15000 | I251: 0 | J251: 15000 | K251: 15000 | L251: 11570.94 | M251: 3429.06 | N251: Meera | O251: Sep | P251: 9

Sheet Customer Segmentation
A3: Customer | B3: Total Orders | C3: Total Spending | D3: Last Purchase Date | E3: Recency Days | F3: Customer Segment
A4: Mansi Patel | B4: =COUNTIF('Sales Data'!$C2:$C251,"Mansi Patel") -> 2 | C4: =SUMIF('Sales Data'!$C2:$C251,"Mansi Patel",'Sales Data'!$K2:$K251) -> 18245 | D4: =_xlfn.MAXIFS('Sales Data'!$B2:$B251,'Sales Data'!$C2:$C251,A4) -> 46204.647 | E4: =INT(MAX('Sales Data'!$B2:$B251)-D4) -> 90 | F4: =IF(AND(B4>=5,C4>=200000,E4<=30),"VIP Customer",IF(AND(B4>=3,C4>=100000,E4<=60),"Loyal Customer",IF(AND(B4>=2,C4>=50000,E4<=90),"Potential Customer",IF(E4>90,"At Risk","Low Value")))) -> Low Value
A5: Chirag Mehta | B5: =COUNTIF('Sales Data'!$C2:$C251,"Chirag Mehta") -> 3 | C5: =SUMIF('Sales Data'!$C3:$C252,"Chirag Mehta",'Sales Data'!$K3:$K252) -> 127000 | D5: =_xlfn.MAXIFS('Sales Data'!$B2:$B251,'Sales Data'!$C2:$C251,A5) -> 46219.808 | E5: =INT(MAX('Sales Data'!$B2:$B251)-D5) -> 74 | F5: =IF(AND(B5>=5,C5>=200000,E5<=30),"VIP Customer",IF(AND(B5>=3,C5>=100000,E5<=60),"Loyal Customer",IF(AND(B5>=2,C5>=50000,E5<=90),"Potential Customer",IF(E5>90,"At Risk","Low Value")))) -> Potential Customer
A6: Rohan Desai | B6: =COUNTIF('Sales Data'!$C2:$C251,"Rohan Desai") -> 4 | C6: =SUMIF('Sales Data'!$C2:$C251,"Rohan Desai",'Sales Data'!$K2:$K251) -> 265300 | D6: =_xlfn.MAXIFS('Sales Data'!$B2:$B251,'Sales Data'!$C2:$C251,A6) -> 46231.434 | E6: =INT(MAX('Sales Data'!$B2:$B251)-D6) -> 63 | F6: =IF(AND(B6>=5,C6>=200000,E6<=30),"VIP Customer",IF(AND(B6>=3,C6>=100000,E6<=60),"Loyal Customer",IF(AND(B6>=2,C6>=50000,E6<=90),"Potential Customer",IF(E6>90,"At Risk","Low Value")))) -> Potential Customer | H6: Customer Segment | I6: Customer Count
A7: Anjali Desai | B7: =COUNTIF('Sales Data'!$C2:$C251,"Anjali Desai") -> 8 | C7: =SUMIF('Sales Data'!$C2:$C251,"Anjali Desai",'Sales Data'!$K2:$K251) -> 165290 | D7: =_xlfn.MAXIFS('Sales Data'!$B2:$B251,'Sales Data'!$C2:$C251,A7) -> 46284.768 | E7: =INT(MAX('Sales Data'!$B2:$B251)-D7) -> 9 | F7: =IF(AND(B7>=5,C7>=200000,E7<=30),"VIP Customer",IF(AND(B7>=3,C7>=100000,E7<=60),"Loyal Customer",IF(AND(B7>=2,C7>=50000,E7<=90),"Potential Customer",IF(E7>90,"At Risk","Low Value")))) -> Loyal Customer | H7: VIP Customer | I7: =COUNTIF(F4:F76,"VIP Customer") -> 3
A8: Nirav Desai | B8: =COUNTIF('Sales Data'!$C2:$C251,"Nirav Desai") -> 6 | C8: =SUMIF('Sales Data'!$C2:$C251,"Nirav Desai",'Sales Data'!$K2:$K251) -> 196820 | D8: =_xlfn.MAXIFS('Sales Data'!$B2:$B251,'Sales Data'!$C2:$C251,A8) -> 46276.483 | E8: =INT(MAX('Sales Data'!$B2:$B251)-D8) -> 18 | F8: =IF(AND(B8>=5,C8>=200000,E8<=30),"VIP Customer",IF(AND(B8>=3,C8>=100000,E8<=60),"Loyal Customer",IF(AND(B8>=2,C8>=50000,E8<=90),"Potential Customer",IF(E8>90,"At Risk","Low Value")))) -> Loyal Customer | H8: Loyal Customer | I8: =COUNTIF(F4:F76,"Loyal Customer") -> 20
A9: Vivek Shah | B9: =COUNTIF('Sales Data'!$C2:$C251,"Vivek Shah") -> 5 | C9: =SUMIF('Sales Data'!$C2:$C251,"Vivek Shah",'Sales Data'!$K2:$K251) -> 424500 | D9: =_xlfn.MAXIFS('Sales Data'!$B2:$B251,'Sales Data'!$C2:$C251,A9) -> 46286.481 | E9: =INT(MAX('Sales Data'!$B2:$B251)-D9) -> 8 | F9: =IF(AND(B9>=5,C9>=200000,E9<=30),"VIP Customer",IF(AND(B9>=3,C9>=100000,E9<=60),"Loyal Customer",IF(AND(B9>=2,C9>=50000,E9<=90),"Potential Customer",IF(E9>90,"At Risk","Low Value")))) -> VIP Customer | H9: Potential Customer | I9: =COUNTIF(F4:F76,"Potential Customer") -> 17
A10: Vishal Mehta | B10: =COUNTIF('Sales Data'!$C2:$C251,"Vishal Mehta") -> 1 | C10: =SUMIF('Sales Data'!$C2:$C251,"Vishal Mehta",'Sales Data'!$K2:$K251) -> 8800 | D10: =_xlfn.MAXIFS('Sales Data'!$B2:$B251,'Sales Data'!$C2:$C251,A10) -> 46036.633 | E10: =INT(MAX('Sales Data'!$B2:$B251)-D10) -> 258 | F10: =IF(AND(B10>=5,C10>=200000,E10<=30),"VIP Customer",IF(AND(B10>=3,C10>=100000,E10<=60),"Loyal Customer",IF(AND(B10>=2,C10>=50000,E10<=90),"Potential Customer",IF(E10>90,"At Risk","Low Value")))) -> At Risk | H10: At Risk | I10: =COUNTIF(F4:F76,"At Risk") -> 22
A11: Aditi Joshi | B11: =COUNTIF('Sales Data'!$C2:$C251,"Aditi Joshi") -> 2 | C11: =SUMIF('Sales Data'!$C2:$C251,"Aditi Joshi",'Sales Data'!$K2:$K251) -> 50300 | D11: =_xlfn.MAXIFS('Sales Data'!$B2:$B251,'Sales Data'!$C2:$C251,A11) -> 46238.783 | E11: =INT(MAX('Sales Data'!$B2:$B251)-D11) -> 55 | F11: =IF(AND(B11>=5,C11>=200000,E11<=30),"VIP Customer",IF(AND(B11>=3,C11>=100000,E11<=60),"Loyal Customer",IF(AND(B11>=2,C11>=50000,E11<=90),"Potential Customer",IF(E11>90,"At Risk","Low Value")))) -> Potential Customer | H11: Low Value | I11: =COUNTIF(F4:F76,"Low Value") -> 11
A12: Hardik Patel | B12: =COUNTIF('Sales Data'!$C2:$C251,"Hardik Patel") -> 2 | C12: =SUMIF('Sales Data'!$C2:$C251,"Hardik Patel",'Sales Data'!$K2:$K251) -> 19710 | D12: =_xlfn.MAXIFS('Sales Data'!$B2:$B251,'Sales Data'!$C2:$C251,A12) -> 46077.621 | E12: =INT(MAX('Sales Data'!$B2:$B251)-D12) -> 217 | F12: =IF(AND(B12>=5,C12>=200000,E12<=30),"VIP Customer",IF(AND(B12>=3,C12>=100000,E12<=60),"Loyal Customer",IF(AND(B12>=2,C12>=50000,E12<=90),"Potential Customer",IF(E12>90,"At Risk","Low Value")))) -> At Risk
A13: Arjun Mehta | B13: =COUNTIF('Sales Data'!$C2:$C251,"Arjun Mehta") -> 2 | C13: =SUMIF('Sales Data'!$C2:$C251,"Arjun Mehta",'Sales Data'!$K2:$K251) -> 17700 | D13: =_xlfn.MAXIFS('Sales Data'!$B2:$B251,'Sales Data'!$C2:$C251,A13) -> 46181.408 | E13: =INT(MAX('Sales Data'!$B2:$B251)-D13) -> 113 | F13: =IF(AND(B13>=5,C13>=200000,E13<=30),"VIP Customer",IF(AND(B13>=3,C13>=100000,E13<=60),"Loyal Customer",IF(AND(B13>=2,C13>=50000,E13<=90),"Potential Customer",IF(E13>90,"At Risk","Low Value")))) -> At Risk
A14: Raj Desai | B14: =COUNTIF('Sales Data'!$C2:$C251,"Raj Desai") -> 3 | C14: =SUMIF('Sales Data'!$C2:$C251,"Raj Desai",'Sales Data'!$K2:$K251) -> 142000 | D14: =_xlfn.MAXIFS('Sales Data'!$B2:$B251,'Sales Data'!$C2:$C251,A14) -> 46283.841 | E14: =INT(MAX('Sales Data'!$B2:$B251)-D14) -> 10 | F14: =IF(AND(B14>=5,C14>=200000,E14<=30),"VIP Customer",IF(AND(B14>=3,C14>=100000,E14<=60),"Loyal Customer",IF(AND(B14>=2,C14>=50000,E14<=90),"Potential Customer",IF(E14>90,"At Risk","Low Value")))) -> Loyal Customer
A15: Jay Joshi | B15: =COUNTIF('Sales Data'!$C2:$C251,"Jay Joshi") -> 8 | C15: =SUMIF('Sales Data'!$C2:$C251,"Jay Joshi",'Sales Data'!$K2:$K251) -> 269640 | D15: =_xlfn.MAXIFS('Sales Data'!$B2:$B251,'Sales Data'!$C2:$C251,A15) -> 46260.781 | E15: =INT(MAX('Sales Data'!$B2:$B251)-D15) -> 33 | F15: =IF(AND(B15>=5,C15>=200000,E15<=30),"VIP Customer",IF(AND(B15>=3,C15>=100000,E15<=60),"Loyal Customer",IF(AND(B15>=2,C15>=50000,E15<=90),"Potential Customer",IF(E15>90,"At Risk","Low Value")))) -> Loyal Customer
A16: Kavya Patel | B16: =COUNTIF('Sales Data'!$C2:$C251,"Kavya Patel") -> 4 | C16: =SUMIF('Sales Data'!$C2:$C251,"Kavya Patel",'Sales Data'!$K2:$K251) -> 123990 | D16: =_xlfn.MAXIFS('Sales Data'!$B2:$B251,'Sales Data'!$C2:$C251,A16) -> 46210.661 | E16: =INT(MAX('Sales Data'!$B2:$B251)-D16) -> 84 | F16: =IF(AND(B16>=5,C16>=200000,E16<=30),"VIP Customer",IF(AND(B16>=3,C16>=100000,E16<=60),"Loyal Customer",IF(AND(B16>=2,C16>=50000,E16<=90),"Potential Customer",IF(E16>90,"At Risk","Low Value")))) -> Potential Customer
A17: Tushar Patel | B17: =COUNTIF('Sales Data'!$C2:$C251,"Tushar Patel") -> 4 | C17: =SUMIF('Sales Data'!$C2:$C251,"Tushar Patel",'Sales Data'!$K2:$K251) -> 20250 | D17: =_xlfn.MAXIFS('Sales Data'!$B2:$B251,'Sales Data'!$C2:$C251,A17) -> 46181.841 | E17: =INT(MAX('Sales Data'!$B2:$B251)-D17) -> 112 | F17: =IF(AND(B17>=5,C17>=200000,E17<=30),"VIP Customer",IF(AND(B17>=3,C17>=100000,E17<=60),"Loyal Customer",IF(AND(B17>=2,C17>=50000,E17<=90),"Potential Customer",IF(E17>90,"At Risk","Low Value")))) -> At Risk
A18: Jinal Desai | B18: =COUNTIF('Sales Data'!$C2:$C251,"Jinal Desai") -> 3 | C18: =SUMIF('Sales Data'!$C2:$C251,"Jinal Desai",'Sales Data'!$K2:$K251) -> 42840 | D18: =_xlfn.MAXIFS('Sales Data'!$B2:$B251,'Sales Data'!$C2:$C251,A18) -> 46164.447 | E18: =INT(MAX('Sales Data'!$B2:$B251)-D18) -> 130 | F18: =IF(AND(B18>=5,C18>=200000,E18<=30),"VIP Customer",IF(AND(B18>=3,C18>=100000,E18<=60),"Loyal Customer",IF(AND(B18>=2,C18>=50000,E18<=90),"Potential Customer",IF(E18>90,"At Risk","Low Value")))) -> At Risk
A19: Pooja Mehta | B19: =COUNTIF('Sales Data'!$C2:$C251,"Pooja Mehta") -> 5 | C19: =SUMIF('Sales Data'!$C2:$C251,"Pooja Mehta",'Sales Data'!$K2:$K251) -> 198880 | D19: =_xlfn.MAXIFS('Sales Data'!$B2:$B251,'Sales Data'!$C2:$C251,A19) -> 46234.702 | E19: =INT(MAX('Sales Data'!$B2:$B251)-D19) -> 60 | F19: =IF(AND(B19>=5,C19>=200000,E19<=30),"VIP Customer",IF(AND(B19>=3,C19>=100000,E19<=60),"Loyal Customer",IF(AND(B19>=2,C19>=50000,E19<=90),"Potential Customer",IF(E19>90,"At Risk","Low Value")))) -> Loyal Customer
A20: Yug Desai | B20: =COUNTIF('Sales Data'!$C2:$C251,"Yug Desai") -> 6 | C20: =SUMIF('Sales Data'!$C2:$C251,"Yug Desai",'Sales Data'!$K2:$K251) -> 123420 | D20: =_xlfn.MAXIFS('Sales Data'!$B2:$B251,'Sales Data'!$C2:$C251,A20) -> 46279.648 | E20: =INT(MAX('Sales Data'!$B2:$B251)-D20) -> 15 | F20: =IF(AND(B20>=5,C20>=200000,E20<=30),"VIP Customer",IF(AND(B20>=3,C20>=100000,E20<=60),"Loyal Customer",IF(AND(B20>=2,C20>=50000,E20<=90),"Potential Customer",IF(E20>90,"At Risk","Low Value")))) -> Loyal Customer
A21: Kunal Mehta | B21: =COUNTIF('Sales Data'!$C2:$C251,"Kunal Mehta") -> 4 | C21: =SUMIF('Sales Data'!$C2:$C251,"Kunal Mehta",'Sales Data'!$K2:$K251) -> 55000 | D21: =_xlfn.MAXIFS('Sales Data'!$B2:$B251,'Sales Data'!$C2:$C251,A21) -> 46275.62 | E21: =INT(MAX('Sales Data'!$B2:$B251)-D21) -> 19 | F21: =IF(AND(B21>=5,C21>=200000,E21<=30),"VIP Customer",IF(AND(B21>=3,C21>=100000,E21<=60),"Loyal Customer",IF(AND(B21>=2,C21>=50000,E21<=90),"Potential Customer",IF(E21>90,"At Risk","Low Value")))) -> Potential Customer
A22: Bhavya Shah | B22: =COUNTIF('Sales Data'!$C2:$C251,"Bhavya Shah") -> 4 | C22: =SUMIF('Sales Data'!$C2:$C251,"Bhavya Shah",'Sales Data'!$K2:$K251) -> 221850 | D22: =_xlfn.MAXIFS('Sales Data'!$B2:$B251,'Sales Data'!$C2:$C251,A22) -> 46204.699 | E22: =INT(MAX('Sales Data'!$B2:$B251)-D22) -> 90 | F22: =IF(AND(B22>=5,C22>=200000,E22<=30),"VIP Customer",IF(AND(B22>=3,C22>=100000,E22<=60),"Loyal Customer",IF(AND(B22>=2,C22>=50000,E22<=90),"Potential Customer",IF(E22>90,"At Risk","Low Value")))) -> Potential Customer
A23: Smit Mehta | B23: =COUNTIF('Sales Data'!$C2:$C251,"Smit Mehta") -> 6 | C23: =SUMIF('Sales Data'!$C2:$C251,"Smit Mehta",'Sales Data'!$K2:$K251) -> 282900 | D23: =_xlfn.MAXIFS('Sales Data'!$B2:$B251,'Sales Data'!$C2:$C251,A23) -> 46180.869 | E23: =INT(MAX('Sales Data'!$B2:$B251)-D23) -> 113 | F23: =IF(AND(B23>=5,C23>=200000,E23<=30),"VIP Customer",IF(AND(B23>=3,C23>=100000,E23<=60),"Loyal Customer",IF(AND(B23>=2,C23>=50000,E23<=90),"Potential Customer",IF(E23>90,"At Risk","Low Value")))) -> At Risk
A24: Neha Shah | B24: =COUNTIF('Sales Data'!$C2:$C251,"Neha Shah") -> 5 | C24: =SUMIF('Sales Data'!$C2:$C251,"Neha Shah",'Sales Data'!$K2:$K251) -> 168800 | D24: =_xlfn.MAXIFS('Sales Data'!$B2:$B251,'Sales Data'!$C2:$C251,A24) -> 46287.55 | E24: =INT(MAX('Sales Data'!$B2:$B251)-D24) -> 7 | F24: =IF(AND(B24>=5,C24>=200000,E24<=30),"VIP Customer",IF(AND(B24>=3,C24>=100000,E24<=60),"Loyal Customer",IF(AND(B24>=2,C24>=50000,E24<=90),"Potential Customer",IF(E24>90,"At Risk","Low Value")))) -> Loyal Customer
A25: Vidhi Shah | B25: =COUNTIF('Sales Data'!$C2:$C251,"Vidhi Shah") -> 2 | C25: =SUMIF('Sales Data'!$C2:$C251,"Vidhi Shah",'Sales Data'!$K2:$K251) -> 57350 | D25: =_xlfn.MAXIFS('Sales Data'!$B2:$B251,'Sales Data'!$C2:$C251,A25) -> 46238.413 | E25: =INT(MAX('Sales Data'!$B2:$B251)-D25) -> 56 | F25: =IF(AND(B25>=5,C25>=200000,E25<=30),"VIP Customer",IF(AND(B25>=3,C25>=100000,E25<=60),"Loyal Customer",IF(AND(B25>=2,C25>=50000,E25<=90),"Potential Customer",IF(E25>90,"At Risk","Low Value")))) -> Potential Customer
A26: Aaradhya Joshi | B26: =COUNTIF('Sales Data'!$C2:$C251,"Aaradhya Joshi") -> 3 | C26: =SUMIF('Sales Data'!$C2:$C251,"Aaradhya Joshi",'Sales Data'!$K2:$K251) -> 214900 | D26: =_xlfn.MAXIFS('Sales Data'!$B2:$B251,'Sales Data'!$C2:$C251,A26) -> 46207.365 | E26: =INT(MAX('Sales Data'!$B2:$B251)-D26) -> 87 | F26: =IF(AND(B26>=5,C26>=200000,E26<=30),"VIP Customer",IF(AND(B26>=3,C26>=100000,E26<=60),"Loyal Customer",IF(AND(B26>=2,C26>=50000,E26<=90),"Potential Customer",IF(E26>90,"At Risk","Low Value")))) -> Potential Customer
A27: Ankit Mehta | B27: =COUNTIF('Sales Data'!$C2:$C251,"Ankit Mehta") -> 4 | C27: =SUMIF('Sales Data'!$C2:$C251,"Ankit Mehta",'Sales Data'!$K2:$K251) -> 98350 | D27: =_xlfn.MAXIFS('Sales Data'!$B2:$B251,'Sales Data'!$C2:$C251,A27) -> 46188.468 | E27: =INT(MAX('Sales Data'!$B2:$B251)-D27) -> 106 | F27: =IF(AND(B27>=5,C27>=200000,E27<=30),"VIP Customer",IF(AND(B27>=3,C27>=100000,E27<=60),"Loyal Customer",IF(AND(B27>=2,C27>=50000,E27<=90),"Potential Customer",IF(E27>90,"At Risk","Low Value")))) -> At Risk
A28: Manav Patel | B28: =COUNTIF('Sales Data'!$C2:$C251,"Manav Patel") -> 5 | C28: =SUMIF('Sales Data'!$C2:$C251,"Manav Patel",'Sales Data'!$K2:$K251) -> 212800 | D28: =_xlfn.MAXIFS('Sales Data'!$B2:$B251,'Sales Data'!$C2:$C251,A28) -> 46247.803 | E28: =INT(MAX('Sales Data'!$B2:$B251)-D28) -> 46 | F28: =IF(AND(B28>=5,C28>=200000,E28<=30),"VIP Customer",IF(AND(B28>=3,C28>=100000,E28<=60),"Loyal Customer",IF(AND(B28>=2,C28>=50000,E28<=90),"Potential Customer",IF(E28>90,"At Risk","Low Value")))) -> Loyal Customer
A29: Riya Mehta | B29: =COUNTIF('Sales Data'!$C2:$C251,"Riya Mehta") -> 2 | C29: =SUMIF('Sales Data'!$C2:$C251,"Riya Mehta",'Sales Data'!$K2:$K251) -> 98525 | D29: =_xlfn.MAXIFS('Sales Data'!$B2:$B251,'Sales Data'!$C2:$C251,A29) -> 46265.616 | E29: =INT(MAX('Sales Data'!$B2:$B251)-D29) -> 29 | F29: =IF(AND(B29>=5,C29>=200000,E29<=30),"VIP Customer",IF(AND(B29>=3,C29>=100000,E29<=60),"Loyal Customer",IF(AND(B29>=2,C29>=50000,E29<=90),"Potential Customer",IF(E29>90,"At Risk","Low Value")))) -> Potential Customer
A30: Isha Joshi | B30: =COUNTIF('Sales Data'!$C2:$C251,"Isha Joshi") -> 2 | C30: =SUMIF('Sales Data'!$C2:$C251,"Isha Joshi",'Sales Data'!$K2:$K251) -> 39950 | D30: =_xlfn.MAXIFS('Sales Data'!$B2:$B251,'Sales Data'!$C2:$C251,A30) -> 46105.779 | E30: =INT(MAX('Sales Data'!$B2:$B251)-D30) -> 188 | F30: =IF(AND(B30>=5,C30>=200000,E30<=30),"VIP Customer",IF(AND(B30>=3,C30>=100000,E30<=60),"Loyal Customer",IF(AND(B30>=2,C30>=50000,E30<=90),"Potential Customer",IF(E30>90,"At Risk","Low Value")))) -> At Risk
A31: Nikhil Joshi | B31: =COUNTIF('Sales Data'!$C2:$C251,"Nikhil Joshi") -> 5 | C31: =SUMIF('Sales Data'!$C2:$C251,"Nikhil Joshi",'Sales Data'!$K2:$K251) -> 200070 | D31: =_xlfn.MAXIFS('Sales Data'!$B2:$B251,'Sales Data'!$C2:$C251,A31) -> 46248.696 | E31: =INT(MAX('Sales Data'!$B2:$B251)-D31) -> 46 | F31: =IF(AND(B31>=5,C31>=200000,E31<=30),"VIP Customer",IF(AND(B31>=3,C31>=100000,E31<=60),"Loyal Customer",IF(AND(B31>=2,C31>=50000,E31<=90),"Potential Customer",IF(E31>90,"At Risk","Low Value")))) -> Loyal Customer
A32: Khushi Mehta | B32: =COUNTIF('Sales Data'!$C2:$C251,"Khushi Mehta") -> 1 | C32: =SUMIF('Sales Data'!$C2:$C251,"Khushi Mehta",'Sales Data'!$K2:$K251) -> 44000 | D32: =_xlfn.MAXIFS('Sales Data'!$B2:$B251,'Sales Data'!$C2:$C251,A32) -> 46070.66 | E32: =INT(MAX('Sales Data'!$B2:$B251)-D32) -> 224 | F32: =IF(AND(B32>=5,C32>=200000,E32<=30),"VIP Customer",IF(AND(B32>=3,C32>=100000,E32<=60),"Loyal Customer",IF(AND(B32>=2,C32>=50000,E32<=90),"Potential Customer",IF(E32>90,"At Risk","Low Value")))) -> At Risk
A33: Nandini Shah | B33: =COUNTIF('Sales Data'!$C2:$C251,"Nandini Shah") -> 4 | C33: =SUMIF('Sales Data'!$C2:$C251,"Nandini Shah",'Sales Data'!$K2:$K251) -> 67050 | D33: =_xlfn.MAXIFS('Sales Data'!$B2:$B251,'Sales Data'!$C2:$C251,A33) -> 46269.822 | E33: =INT(MAX('Sales Data'!$B2:$B251)-D33) -> 24 | F33: =IF(AND(B33>=5,C33>=200000,E33<=30),"VIP Customer",IF(AND(B33>=3,C33>=100000,E33<=60),"Loyal Customer",IF(AND(B33>=2,C33>=50000,E33<=90),"Potential Customer",IF(E33>90,"At Risk","Low Value")))) -> Potential Customer
A34: Darsh Shah | B34: =COUNTIF('Sales Data'!$C2:$C251,"Darsh Shah") -> 3 | C34: =SUMIF('Sales Data'!$C2:$C251,"Darsh Shah",'Sales Data'!$K2:$K251) -> 67960 | D34: =_xlfn.MAXIFS('Sales Data'!$B2:$B251,'Sales Data'!$C2:$C251,A34) -> 46194.446 | E34: =INT(MAX('Sales Data'!$B2:$B251)-D34) -> 100 | F34: =IF(AND(B34>=5,C34>=200000,E34<=30),"VIP Customer",IF(AND(B34>=3,C34>=100000,E34<=60),"Loyal Customer",IF(AND(B34>=2,C34>=50000,E34<=90),"Potential Customer",IF(E34>90,"At Risk","Low Value")))) -> At Risk
A35: Nisha Joshi | B35: =COUNTIF('Sales Data'!$C2:$C251,"Nisha Joshi") -> 7 | C35: =SUMIF('Sales Data'!$C2:$C251,"Nisha Joshi",'Sales Data'!$K2:$K251) -> 306500 | D35: =_xlfn.MAXIFS('Sales Data'!$B2:$B251,'Sales Data'!$C2:$C251,A35) -> 46242.727 | E35: =INT(MAX('Sales Data'!$B2:$B251)-D35) -> 51 | F35: =IF(AND(B35>=5,C35>=200000,E35<=30),"VIP Customer",IF(AND(B35>=3,C35>=100000,E35<=60),"Loyal Customer",IF(AND(B35>=2,C35>=50000,E35<=90),"Potential Customer",IF(E35>90,"At Risk","Low Value")))) -> Loyal Customer
A36: Abhishek Mehta | B36: =COUNTIF('Sales Data'!$C2:$C251,"Abhishek Mehta") -> 2 | C36: =SUMIF('Sales Data'!$C2:$C251,"Abhishek Mehta",'Sales Data'!$K2:$K251) -> 26300 | D36: =_xlfn.MAXIFS('Sales Data'!$B2:$B251,'Sales Data'!$C2:$C251,A36) -> 46136.397 | E36: =INT(MAX('Sales Data'!$B2:$B251)-D36) -> 158 | F36: =IF(AND(B36>=5,C36>=200000,E36<=30),"VIP Customer",IF(AND(B36>=3,C36>=100000,E36<=60),"Loyal Customer",IF(AND(B36>=2,C36>=50000,E36<=90),"Potential Customer",IF(E36>90,"At Risk","Low Value")))) -> At Risk
A37: Akash Patel | B37: =COUNTIF('Sales Data'!$C2:$C251,"Akash Patel") -> 3 | C37: =SUMIF('Sales Data'!$C2:$C251,"Akash Patel",'Sales Data'!$K2:$K251) -> 24015 | D37: =_xlfn.MAXIFS('Sales Data'!$B2:$B251,'Sales Data'!$C2:$C251,A37) -> 46215.791 | E37: =INT(MAX('Sales Data'!$B2:$B251)-D37) -> 78 | F37: =IF(AND(B37>=5,C37>=200000,E37<=30),"VIP Customer",IF(AND(B37>=3,C37>=100000,E37<=60),"Loyal Customer",IF(AND(B37>=2,C37>=50000,E37<=90),"Potential Customer",IF(E37>90,"At Risk","Low Value")))) -> Low Value
A38: Meet Desai | B38: =COUNTIF('Sales Data'!$C2:$C251,"Meet Desai") -> 4 | C38: =SUMIF('Sales Data'!$C2:$C251,"Meet Desai",'Sales Data'!$K2:$K251) -> 122700 | D38: =_xlfn.MAXIFS('Sales Data'!$B2:$B251,'Sales Data'!$C2:$C251,A38) -> 46269.742 | E38: =INT(MAX('Sales Data'!$B2:$B251)-D38) -> 24 | F38: =IF(AND(B38>=5,C38>=200000,E38<=30),"VIP Customer",IF(AND(B38>=3,C38>=100000,E38<=60),"Loyal Customer",IF(AND(B38>=2,C38>=50000,E38<=90),"Potential Customer",IF(E38>90,"At Risk","Low Value")))) -> Loyal Customer
A39: Karan Desai | B39: =COUNTIF('Sales Data'!$C2:$C251,"Karan Desai") -> 5 | C39: =SUMIF('Sales Data'!$C2:$C251,"Karan Desai",'Sales Data'!$K2:$K251) -> 484400 | D39: =_xlfn.MAXIFS('Sales Data'!$B2:$B251,'Sales Data'!$C2:$C251,A39) -> 46257.714 | E39: =INT(MAX('Sales Data'!$B2:$B251)-D39) -> 37 | F39: =IF(AND(B39>=5,C39>=200000,E39<=30),"VIP Customer",IF(AND(B39>=3,C39>=100000,E39<=60),"Loyal Customer",IF(AND(B39>=2,C39>=50000,E39<=90),"Potential Customer",IF(E39>90,"At Risk","Low Value")))) -> Loyal Customer
A40: Jatin Desai | B40: =COUNTIF('Sales Data'!$C2:$C251,"Jatin Desai") -> 4 | C40: =SUMIF('Sales Data'!$C2:$C251,"Jatin Desai",'Sales Data'!$K2:$K251) -> 36230 | D40: =_xlfn.MAXIFS('Sales Data'!$B2:$B251,'Sales Data'!$C2:$C251,A40) -> 46236.854 | E40: =INT(MAX('Sales Data'!$B2:$B251)-D40) -> 57 | F40: =IF(AND(B40>=5,C40>=200000,E40<=30),"VIP Customer",IF(AND(B40>=3,C40>=100000,E40<=60),"Loyal Customer",IF(AND(B40>=2,C40>=50000,E40<=90),"Potential Customer",IF(E40>90,"At Risk","Low Value")))) -> Low Value
A41: Darshil Desai | B41: =COUNTIF('Sales Data'!$C2:$C251,"Darshil Desai") -> 5 | C41: =SUMIF('Sales Data'!$C2:$C251,"Darshil Desai",'Sales Data'!$K2:$K251) -> 67520 | D41: =_xlfn.MAXIFS('Sales Data'!$B2:$B251,'Sales Data'!$C2:$C251,A41) -> 46282.594 | E41: =INT(MAX('Sales Data'!$B2:$B251)-D41) -> 12 | F41: =IF(AND(B41>=5,C41>=200000,E41<=30),"VIP Customer",IF(AND(B41>=3,C41>=100000,E41<=60),"Loyal Customer",IF(AND(B41>=2,C41>=50000,E41<=90),"Potential Customer",IF(E41>90,"At Risk","Low Value")))) -> Potential Customer
A42: Meera Shah | B42: =COUNTIF('Sales Data'!$C2:$C251,"Meera Shah") -> 5 | C42: =SUMIF('Sales Data'!$C2:$C251,"Meera Shah",'Sales Data'!$K2:$K251) -> 149600 | D42: =_xlfn.MAXIFS('Sales Data'!$B2:$B251,'Sales Data'!$C2:$C251,A42) -> 46157.647 | E42: =INT(MAX('Sales Data'!$B2:$B251)-D42) -> 137 | F42: =IF(AND(B42>=5,C42>=200000,E42<=30),"VIP Customer",IF(AND(B42>=3,C42>=100000,E42<=60),"Loyal Customer",IF(AND(B42>=2,C42>=50000,E42<=90),"Potential Customer",IF(E42>90,"At Risk","Low Value")))) -> At Risk
A43: Rahul Mehta | B43: =COUNTIF('Sales Data'!$C2:$C251,"Rahul Mehta") -> 2 | C43: =SUMIF('Sales Data'!$C2:$C251,"Rahul Mehta",'Sales Data'!$K2:$K251) -> 263050 | D43: =_xlfn.MAXIFS('Sales Data'!$B2:$B251,'Sales Data'!$C2:$C251,A43) -> 46205.6 | E43: =INT(MAX('Sales Data'!$B2:$B251)-D43) -> 89 | F43: =IF(AND(B43>=5,C43>=200000,E43<=30),"VIP Customer",IF(AND(B43>=3,C43>=100000,E43<=60),"Loyal Customer",IF(AND(B43>=2,C43>=50000,E43<=90),"Potential Customer",IF(E43>90,"At Risk","Low Value")))) -> Potential Customer
A44: Komal Shah | B44: =COUNTIF('Sales Data'!$C2:$C251,"Komal Shah") -> 5 | C44: =SUMIF('Sales Data'!$C2:$C251,"Komal Shah",'Sales Data'!$K2:$K251) -> 53670 | D44: =_xlfn.MAXIFS('Sales Data'!$B2:$B251,'Sales Data'!$C2:$C251,A44) -> 46234.757 | E44: =INT(MAX('Sales Data'!$B2:$B251)-D44) -> 59 | F44: =IF(AND(B44>=5,C44>=200000,E44<=30),"VIP Customer",IF(AND(B44>=3,C44>=100000,E44<=60),"Loyal Customer",IF(AND(B44>=2,C44>=50000,E44<=90),"Potential Customer",IF(E44>90,"At Risk","Low Value")))) -> Potential Customer
A45: Maulik Patel | B45: =COUNTIF('Sales Data'!$C2:$C251,"Maulik Patel") -> 4 | C45: =SUMIF('Sales Data'!$C2:$C251,"Maulik Patel",'Sales Data'!$K2:$K251) -> 328750 | D45: =_xlfn.MAXIFS('Sales Data'!$B2:$B251,'Sales Data'!$C2:$C251,A45) -> 46256.576 | E45: =INT(MAX('Sales Data'!$B2:$B251)-D45) -> 38 | F45: =IF(AND(B45>=5,C45>=200000,E45<=30),"VIP Customer",IF(AND(B45>=3,C45>=100000,E45<=60),"Loyal Customer",IF(AND(B45>=2,C45>=50000,E45<=90),"Potential Customer",IF(E45>90,"At Risk","Low Value")))) -> Loyal Customer
A46: Palak Joshi | B46: =COUNTIF('Sales Data'!$C2:$C251,"Palak Joshi") -> 2 | C46: =SUMIF('Sales Data'!$C2:$C251,"Palak Joshi",'Sales Data'!$K2:$K251) -> 11400 | D46: =_xlfn.MAXIFS('Sales Data'!$B2:$B251,'Sales Data'!$C2:$C251,A46) -> 46210.739 | E46: =INT(MAX('Sales Data'!$B2:$B251)-D46) -> 83 | F46: =IF(AND(B46>=5,C46>=200000,E46<=30),"VIP Customer",IF(AND(B46>=3,C46>=100000,E46<=60),"Loyal Customer",IF(AND(B46>=2,C46>=50000,E46<=90),"Potential Customer",IF(E46>90,"At Risk","Low Value")))) -> Low Value
A47: Heena Joshi | B47: =COUNTIF('Sales Data'!$C2:$C251,"Heena Joshi") -> 4 | C47: =SUMIF('Sales Data'!$C2:$C251,"Heena Joshi",'Sales Data'!$K2:$K251) -> 26580 | D47: =_xlfn.MAXIFS('Sales Data'!$B2:$B251,'Sales Data'!$C2:$C251,A47) -> 46231.484 | E47: =INT(MAX('Sales Data'!$B2:$B251)-D47) -> 63 | F47: =IF(AND(B47>=5,C47>=200000,E47<=30),"VIP Customer",IF(AND(B47>=3,C47>=100000,E47<=60),"Loyal Customer",IF(AND(B47>=2,C47>=50000,E47<=90),"Potential Customer",IF(E47>90,"At Risk","Low Value")))) -> Low Value
A48: Bhavin Desai | B48: =COUNTIF('Sales Data'!$C2:$C251,"Bhavin Desai") -> 3 | C48: =SUMIF('Sales Data'!$C2:$C251,"Bhavin Desai",'Sales Data'!$K2:$K251) -> 498750 | D48: =_xlfn.MAXIFS('Sales Data'!$B2:$B251,'Sales Data'!$C2:$C251,A48) -> 46178.529 | E48: =INT(MAX('Sales Data'!$B2:$B251)-D48) -> 116 | F48: =IF(AND(B48>=5,C48>=200000,E48<=30),"VIP Customer",IF(AND(B48>=3,C48>=100000,E48<=60),"Loyal Customer",IF(AND(B48>=2,C48>=50000,E48<=90),"Potential Customer",IF(E48>90,"At Risk","Low Value")))) -> At Risk
A49: Krupa Shah | B49: =COUNTIF('Sales Data'!$C2:$C251,"Krupa Shah") -> 2 | C49: =SUMIF('Sales Data'!$C2:$C251,"Krupa Shah",'Sales Data'!$K2:$K251) -> 330000 | D49: =_xlfn.MAXIFS('Sales Data'!$B2:$B251,'Sales Data'!$C2:$C251,A49) -> 46282.835 | E49: =INT(MAX('Sales Data'!$B2:$B251)-D49) -> 11 | F49: =IF(AND(B49>=5,C49>=200000,E49<=30),"VIP Customer",IF(AND(B49>=3,C49>=100000,E49<=60),"Loyal Customer",IF(AND(B49>=2,C49>=50000,E49<=90),"Potential Customer",IF(E49>90,"At Risk","Low Value")))) -> Potential Customer
A50: Ronak Patel | B50: =COUNTIF('Sales Data'!$C2:$C251,"Ronak Patel") -> 1 | C50: =SUMIF('Sales Data'!$C2:$C251,"Ronak Patel",'Sales Data'!$K2:$K251) -> 2975 | D50: =_xlfn.MAXIFS('Sales Data'!$B2:$B251,'Sales Data'!$C2:$C251,A50) -> 46105.765 | E50: =INT(MAX('Sales Data'!$B2:$B251)-D50) -> 188 | F50: =IF(AND(B50>=5,C50>=200000,E50<=30),"VIP Customer",IF(AND(B50>=3,C50>=100000,E50<=60),"Loyal Customer",IF(AND(B50>=2,C50>=50000,E50<=90),"Potential Customer",IF(E50>90,"At Risk","Low Value")))) -> At Risk
A51: Aarav Patel | B51: =COUNTIF('Sales Data'!$C2:$C251,"Aarav Patel") -> 7 | C51: =SUMIF('Sales Data'!$C2:$C251,"Aarav Patel",'Sales Data'!$K2:$K251) -> 324785 | D51: =_xlfn.MAXIFS('Sales Data'!$B2:$B251,'Sales Data'!$C2:$C251,A51) -> 46266.459 | E51: =INT(MAX('Sales Data'!$B2:$B251)-D51) -> 28 | F51: =IF(AND(B51>=5,C51>=200000,E51<=30),"VIP Customer",IF(AND(B51>=3,C51>=100000,E51<=60),"Loyal Customer",IF(AND(B51>=2,C51>=50000,E51<=90),"Potential Customer",IF(E51>90,"At Risk","Low Value")))) -> VIP Customer
A52: Yash Shah | B52: =COUNTIF('Sales Data'!$C2:$C251,"Yash Shah") -> 5 | C52: =SUMIF('Sales Data'!$C2:$C251,"Yash Shah",'Sales Data'!$K2:$K251) -> 196300 | D52: =_xlfn.MAXIFS('Sales Data'!$B2:$B251,'Sales Data'!$C2:$C251,A52) -> 46269.647 | E52: =INT(MAX('Sales Data'!$B2:$B251)-D52) -> 25 | F52: =IF(AND(B52>=5,C52>=200000,E52<=30),"VIP Customer",IF(AND(B52>=3,C52>=100000,E52<=60),"Loyal Customer",IF(AND(B52>=2,C52>=50000,E52<=90),"Potential Customer",IF(E52>90,"At Risk","Low Value")))) -> Loyal Customer
A53: Rupal Joshi | B53: =COUNTIF('Sales Data'!$C2:$C251,"Rupal Joshi") -> 2 | C53: =SUMIF('Sales Data'!$C2:$C251,"Rupal Joshi",'Sales Data'!$K2:$K251) -> 30900 | D53: =_xlfn.MAXIFS('Sales Data'!$B2:$B251,'Sales Data'!$C2:$C251,A53) -> 46179.852 | E53: =INT(MAX('Sales Data'!$B2:$B251)-D53) -> 114 | F53: =IF(AND(B53>=5,C53>=200000,E53<=30),"VIP Customer",IF(AND(B53>=3,C53>=100000,E53<=60),"Loyal Customer",IF(AND(B53>=2,C53>=50000,E53<=90),"Potential Customer",IF(E53>90,"At Risk","Low Value")))) -> At Risk
A54: Krish Joshi | B54: =COUNTIF('Sales Data'!$C2:$C251,"Krish Joshi") -> 5 | C54: =SUMIF('Sales Data'!$C2:$C251,"Krish Joshi",'Sales Data'!$K2:$K251) -> 65600 | D54: =_xlfn.MAXIFS('Sales Data'!$B2:$B251,'Sales Data'!$C2:$C251,A54) -> 46284.345 | E54: =INT(MAX('Sales Data'!$B2:$B251)-D54) -> 10 | F54: =IF(AND(B54>=5,C54>=200000,E54<=30),"VIP Customer",IF(AND(B54>=3,C54>=100000,E54<=60),"Loyal Customer",IF(AND(B54>=2,C54>=50000,E54<=90),"Potential Customer",IF(E54>90,"At Risk","Low Value")))) -> Potential Customer
A55: Vatsal Desai | B55: =COUNTIF('Sales Data'!$C2:$C251,"Vatsal Desai") -> 3 | C55: =SUMIF('Sales Data'!$C2:$C251,"Vatsal Desai",'Sales Data'!$K2:$K251) -> 141000 | D55: =_xlfn.MAXIFS('Sales Data'!$B2:$B251,'Sales Data'!$C2:$C251,A55) -> 46243.656 | E55: =INT(MAX('Sales Data'!$B2:$B251)-D55) -> 51 | F55: =IF(AND(B55>=5,C55>=200000,E55<=30),"VIP Customer",IF(AND(B55>=3,C55>=100000,E55<=60),"Loyal Customer",IF(AND(B55>=2,C55>=50000,E55<=90),"Potential Customer",IF(E55>90,"At Risk","Low Value")))) -> Loyal Customer
A56: Sneha Shah | B56: =COUNTIF('Sales Data'!$C2:$C251,"Sneha Shah") -> 3 | C56: =SUMIF('Sales Data'!$C2:$C251,"Sneha Shah",'Sales Data'!$K2:$K251) -> 175420 | D56: =_xlfn.MAXIFS('Sales Data'!$B2:$B251,'Sales Data'!$C2:$C251,A56) -> 46283.434 | E56: =INT(MAX('Sales Data'!$B2:$B251)-D56) -> 11 | F56: =IF(AND(B56>=5,C56>=200000,E56<=30),"VIP Customer",IF(AND(B56>=3,C56>=100000,E56<=60),"Loyal Customer",IF(AND(B56>=2,C56>=50000,E56<=90),"Potential Customer",IF(E56>90,"At Risk","Low Value")))) -> Loyal Customer
A57: Amit Patel | B57: =COUNTIF('Sales Data'!$C2:$C251,"Amit Patel") -> 1 | C57: =SUMIF('Sales Data'!$C2:$C251,"Amit Patel",'Sales Data'!$K2:$K251) -> 24000 | D57: =_xlfn.MAXIFS('Sales Data'!$B2:$B251,'Sales Data'!$C2:$C251,A57) -> 46133.738 | E57: =INT(MAX('Sales Data'!$B2:$B251)-D57) -> 160 | F57: =IF(AND(B57>=5,C57>=200000,E57<=30),"VIP Customer",IF(AND(B57>=3,C57>=100000,E57<=60),"Loyal Customer",IF(AND(B57>=2,C57>=50000,E57<=90),"Potential Customer",IF(E57>90,"At Risk","Low Value")))) -> At Risk
A58: Mitali Shah | B58: =COUNTIF('Sales Data'!$C2:$C251,"Mitali Shah") -> 5 | C58: =SUMIF('Sales Data'!$C2:$C251,"Mitali Shah",'Sales Data'!$K2:$K251) -> 326150 | D58: =_xlfn.MAXIFS('Sales Data'!$B2:$B251,'Sales Data'!$C2:$C251,A58) -> 46294.715 | E58: =INT(MAX('Sales Data'!$B2:$B251)-D58) -> 0 | F58: =IF(AND(B58>=5,C58>=200000,E58<=30),"VIP Customer",IF(AND(B58>=3,C58>=100000,E58<=60),"Loyal Customer",IF(AND(B58>=2,C58>=50000,E58<=90),"Potential Customer",IF(E58>90,"At Risk","Low Value")))) -> VIP Customer
A59: Varun Patel | B59: =COUNTIF('Sales Data'!$C2:$C251,"Varun Patel") -> 4 | C59: =SUMIF('Sales Data'!$C2:$C251,"Varun Patel",'Sales Data'!$K2:$K251) -> 130000 | D59: =_xlfn.MAXIFS('Sales Data'!$B2:$B251,'Sales Data'!$C2:$C251,A59) -> 46292.4 | E59: =INT(MAX('Sales Data'!$B2:$B251)-D59) -> 2 | F59: =IF(AND(B59>=5,C59>=200000,E59<=30),"VIP Customer",IF(AND(B59>=3,C59>=100000,E59<=60),"Loyal Customer",IF(AND(B59>=2,C59>=50000,E59<=90),"Potential Customer",IF(E59>90,"At Risk","Low Value")))) -> Loyal Customer
A60: Vraj Desai | B60: =COUNTIF('Sales Data'!$C2:$C251,"Vraj Desai") -> 1 | C60: =SUMIF('Sales Data'!$C2:$C251,"Vraj Desai",'Sales Data'!$K2:$K251) -> 5400 | D60: =_xlfn.MAXIFS('Sales Data'!$B2:$B251,'Sales Data'!$C2:$C251,A60) -> 46144.461 | E60: =INT(MAX('Sales Data'!$B2:$B251)-D60) -> 150 | F60: =IF(AND(B60>=5,C60>=200000,E60<=30),"VIP Customer",IF(AND(B60>=3,C60>=100000,E60<=60),"Loyal Customer",IF(AND(B60>=2,C60>=50000,E60<=90),"Potential Customer",IF(E60>90,"At Risk","Low Value")))) -> At Risk
A61: Parth Joshi | B61: =COUNTIF('Sales Data'!$C2:$C251,"Parth Joshi") -> 4 | C61: =SUMIF('Sales Data'!$C2:$C251,"Parth Joshi",'Sales Data'!$K2:$K251) -> 103850 | D61: =_xlfn.MAXIFS('Sales Data'!$B2:$B251,'Sales Data'!$C2:$C251,A61) -> 46201.684 | E61: =INT(MAX('Sales Data'!$B2:$B251)-D61) -> 93 | F61: =IF(AND(B61>=5,C61>=200000,E61<=30),"VIP Customer",IF(AND(B61>=3,C61>=100000,E61<=60),"Loyal Customer",IF(AND(B61>=2,C61>=50000,E61<=90),"Potential Customer",IF(E61>90,"At Risk","Low Value")))) -> At Risk
A62: Diya Patel | B62: =COUNTIF('Sales Data'!$C2:$C251,"Diya Patel") -> 4 | C62: =SUMIF('Sales Data'!$C2:$C251,"Diya Patel",'Sales Data'!$K2:$K251) -> 203910 | D62: =_xlfn.MAXIFS('Sales Data'!$B2:$B251,'Sales Data'!$C2:$C251,A62) -> 46255.857 | E62: =INT(MAX('Sales Data'!$B2:$B251)-D62) -> 38 | F62: =IF(AND(B62>=5,C62>=200000,E62<=30),"VIP Customer",IF(AND(B62>=3,C62>=100000,E62<=60),"Loyal Customer",IF(AND(B62>=2,C62>=50000,E62<=90),"Potential Customer",IF(E62>90,"At Risk","Low Value")))) -> Loyal Customer
A63: Shreya Joshi | B63: =COUNTIF('Sales Data'!$C11:$C260,"Shreya Joshi") -> 3 | C63: =SUMIF('Sales Data'!$C2:$C251,"Shreya Joshi",'Sales Data'!$K2:$K251) -> 74530 | D63: =_xlfn.MAXIFS('Sales Data'!$B2:$B251,'Sales Data'!$C2:$C251,A63) -> 46264.354 | E63: =INT(MAX('Sales Data'!$B2:$B251)-D63) -> 30 | F63: =IF(AND(B63>=5,C63>=200000,E63<=30),"VIP Customer",IF(AND(B63>=3,C63>=100000,E63<=60),"Loyal Customer",IF(AND(B63>=2,C63>=50000,E63<=90),"Potential Customer",IF(E63>90,"At Risk","Low Value")))) -> Potential Customer
A64: Mihir Patel | B64: =COUNTIF('Sales Data'!$C11:$C260,"Mihir Patel") -> 3 | C64: =SUMIF('Sales Data'!$C2:$C251,"Mihir Patel",'Sales Data'!$K2:$K251) -> 16800 | D64: =_xlfn.MAXIFS('Sales Data'!$B2:$B251,'Sales Data'!$C2:$C251,A64) -> 46244.454 | E64: =INT(MAX('Sales Data'!$B2:$B251)-D64) -> 50 | F64: =IF(AND(B64>=5,C64>=200000,E64<=30),"VIP Customer",IF(AND(B64>=3,C64>=100000,E64<=60),"Loyal Customer",IF(AND(B64>=2,C64>=50000,E64<=90),"Potential Customer",IF(E64>90,"At Risk","Low Value")))) -> Low Value
A65: Hetal Shah | B65: =COUNTIF('Sales Data'!$C11:$C260,"Hetal Shah") -> 1 | C65: =SUMIF('Sales Data'!$C2:$C251,"Hetal Shah",'Sales Data'!$K2:$K251) -> 9900 | D65: =_xlfn.MAXIFS('Sales Data'!$B2:$B251,'Sales Data'!$C2:$C251,A65) -> 46169.785 | E65: =INT(MAX('Sales Data'!$B2:$B251)-D65) -> 124 | F65: =IF(AND(B65>=5,C65>=200000,E65<=30),"VIP Customer",IF(AND(B65>=3,C65>=100000,E65<=60),"Loyal Customer",IF(AND(B65>=2,C65>=50000,E65<=90),"Potential Customer",IF(E65>90,"At Risk","Low Value")))) -> At Risk
A66: Priya Joshi | B66: =COUNTIF('Sales Data'!$C11:$C260,"Priya Joshi") -> 5 | C66: =SUMIF('Sales Data'!$C2:$C251,"Priya Joshi",'Sales Data'!$K2:$K251) -> 448200 | D66: =_xlfn.MAXIFS('Sales Data'!$B2:$B251,'Sales Data'!$C2:$C251,A66) -> 46240.817 | E66: =INT(MAX('Sales Data'!$B2:$B251)-D66) -> 53 | F66: =IF(AND(B66>=5,C66>=200000,E66<=30),"VIP Customer",IF(AND(B66>=3,C66>=100000,E66<=60),"Loyal Customer",IF(AND(B66>=2,C66>=50000,E66<=90),"Potential Customer",IF(E66>90,"At Risk","Low Value")))) -> Loyal Customer
A67: Jaydeep Mehta | B67: =COUNTIF('Sales Data'!$C11:$C260,"Jaydeep Mehta") -> 1 | C67: =SUMIF('Sales Data'!$C2:$C251,"Jaydeep Mehta",'Sales Data'!$K2:$K251) -> 12000 | D67: =_xlfn.MAXIFS('Sales Data'!$B2:$B251,'Sales Data'!$C2:$C251,A67) -> 46170.835 | E67: =INT(MAX('Sales Data'!$B2:$B251)-D67) -> 123 | F67: =IF(AND(B67>=5,C67>=200000,E67<=30),"VIP Customer",IF(AND(B67>=3,C67>=100000,E67<=60),"Loyal Customer",IF(AND(B67>=2,C67>=50000,E67<=90),"Potential Customer",IF(E67>90,"At Risk","Low Value")))) -> At Risk
A68: Het Desai | B68: =COUNTIF('Sales Data'!$C11:$C260,"Het Desai") -> 1 | C68: =SUMIF('Sales Data'!$C2:$C251,"Het Desai",'Sales Data'!$K2:$K251) -> 25500 | D68: =_xlfn.MAXIFS('Sales Data'!$B2:$B251,'Sales Data'!$C2:$C251,A68) -> 46193.767 | E68: =INT(MAX('Sales Data'!$B2:$B251)-D68) -> 100 | F68: =IF(AND(B68>=5,C68>=200000,E68<=30),"VIP Customer",IF(AND(B68>=3,C68>=100000,E68<=60),"Loyal Customer",IF(AND(B68>=2,C68>=50000,E68<=90),"Potential Customer",IF(E68>90,"At Risk","Low Value")))) -> At Risk
A69: Simran Joshi | B69: =COUNTIF('Sales Data'!$C11:$C260,"Simran Joshi") -> 1 | C69: =SUMIF('Sales Data'!$C2:$C251,"Simran Joshi",'Sales Data'!$K2:$K251) -> 34000 | D69: =_xlfn.MAXIFS('Sales Data'!$B2:$B251,'Sales Data'!$C2:$C251,A69) -> 46200.583 | E69: =INT(MAX('Sales Data'!$B2:$B251)-D69) -> 94 | F69: =IF(AND(B69>=5,C69>=200000,E69<=30),"VIP Customer",IF(AND(B69>=3,C69>=100000,E69<=60),"Loyal Customer",IF(AND(B69>=2,C69>=50000,E69<=90),"Potential Customer",IF(E69>90,"At Risk","Low Value")))) -> At Risk
A70: Sahil Mehta | B70: =COUNTIF('Sales Data'!$C11:$C260,"Sahil Mehta") -> 1 | C70: =SUMIF('Sales Data'!$C2:$C251,"Sahil Mehta",'Sales Data'!$K2:$K251) -> 4800 | D70: =_xlfn.MAXIFS('Sales Data'!$B2:$B251,'Sales Data'!$C2:$C251,A70) -> 46206.808 | E70: =INT(MAX('Sales Data'!$B2:$B251)-D70) -> 87 | F70: =IF(AND(B70>=5,C70>=200000,E70<=30),"VIP Customer",IF(AND(B70>=3,C70>=100000,E70<=60),"Loyal Customer",IF(AND(B70>=2,C70>=50000,E70<=90),"Potential Customer",IF(E70>90,"At Risk","Low Value")))) -> Low Value
A71: Aarohi Desai | B71: =COUNTIF('Sales Data'!$C11:$C260,"Diya Patel") -> 4 | C71: =SUMIF('Sales Data'!$C2:$C251,"Aarohi Desai",'Sales Data'!$K2:$K251) -> 52250 | D71: =_xlfn.MAXIFS('Sales Data'!$B2:$B251,'Sales Data'!$C2:$C251,A71) -> 46215.495 | E71: =INT(MAX('Sales Data'!$B2:$B251)-D71) -> 79 | F71: =IF(AND(B71>=5,C71>=200000,E71<=30),"VIP Customer",IF(AND(B71>=3,C71>=100000,E71<=60),"Loyal Customer",IF(AND(B71>=2,C71>=50000,E71<=90),"Potential Customer",IF(E71>90,"At Risk","Low Value")))) -> Potential Customer
A72: Manish Mehta | B72: =COUNTIF('Sales Data'!$C20:$C269,"Manish Mehta") -> 3 | C72: =SUMIF('Sales Data'!$C2:$C251,"Manish Mehta",'Sales Data'!$K2:$K251) -> 42500 | D72: =_xlfn.MAXIFS('Sales Data'!$B2:$B251,'Sales Data'!$C2:$C251,A72) -> 46271.704 | E72: =INT(MAX('Sales Data'!$B2:$B251)-D72) -> 23 | F72: =IF(AND(B72>=5,C72>=200000,E72<=30),"VIP Customer",IF(AND(B72>=3,C72>=100000,E72<=60),"Loyal Customer",IF(AND(B72>=2,C72>=50000,E72<=90),"Potential Customer",IF(E72>90,"At Risk","Low Value")))) -> Low Value
A73: Ayesha Patel | B73: =COUNTIF('Sales Data'!$C20:$C269,"Ayesha Patel") -> 3 | C73: =SUMIF('Sales Data'!$C2:$C251,"Ayesha Patel",'Sales Data'!$K2:$K251) -> 435250 | D73: =_xlfn.MAXIFS('Sales Data'!$B2:$B251,'Sales Data'!$C2:$C251,A73) -> 46262.688 | E73: =INT(MAX('Sales Data'!$B2:$B251)-D73) -> 32 | F73: =IF(AND(B73>=5,C73>=200000,E73<=30),"VIP Customer",IF(AND(B73>=3,C73>=100000,E73<=60),"Loyal Customer",IF(AND(B73>=2,C73>=50000,E73<=90),"Potential Customer",IF(E73>90,"At Risk","Low Value")))) -> Loyal Customer
A74: Kinjal Joshi | B74: =COUNTIF('Sales Data'!$C20:$C269,"Kinjal Joshi") -> 1 | C74: =SUMIF('Sales Data'!$C2:$C251,"Kinjal Joshi",'Sales Data'!$K2:$K251) -> 220000 | D74: =_xlfn.MAXIFS('Sales Data'!$B2:$B251,'Sales Data'!$C2:$C251,A74) -> 46226.39 | E74: =INT(MAX('Sales Data'!$B2:$B251)-D74) -> 68 | F74: =IF(AND(B74>=5,C74>=200000,E74<=30),"VIP Customer",IF(AND(B74>=3,C74>=100000,E74<=60),"Loyal Customer",IF(AND(B74>=2,C74>=50000,E74<=90),"Potential Customer",IF(E74>90,"At Risk","Low Value")))) -> Low Value
A75: Roshni Shah | B75: =COUNTIF('Sales Data'!$C20:$C269,"Roshni Shah") -> 1 | C75: =SUMIF('Sales Data'!$C2:$C251,"Roshni Shah",'Sales Data'!$K2:$K251) -> 57000 | D75: =_xlfn.MAXIFS('Sales Data'!$B2:$B251,'Sales Data'!$C2:$C251,A75) -> 46266.711 | E75: =INT(MAX('Sales Data'!$B2:$B251)-D75) -> 28 | F75: =IF(AND(B75>=5,C75>=200000,E75<=30),"VIP Customer",IF(AND(B75>=3,C75>=100000,E75<=60),"Loyal Customer",IF(AND(B75>=2,C75>=50000,E75<=90),"Potential Customer",IF(E75>90,"At Risk","Low Value")))) -> Low Value
A76: Dhruv Desai | B76: =COUNTIF('Sales Data'!$C20:$C269,"Dhruv Desai") -> 1 | C76: =SUMIF('Sales Data'!$C2:$C251,"Dhruv Desai",'Sales Data'!$K2:$K251) -> 233750 | D76: =_xlfn.MAXIFS('Sales Data'!$B2:$B251,'Sales Data'!$C2:$C251,A76) -> 46283.855 | E76: =INT(MAX('Sales Data'!$B2:$B251)-D76) -> 10 | F76: =IF(AND(B76>=5,C76>=200000,E76<=30),"VIP Customer",IF(AND(B76>=3,C76>=100000,E76<=60),"Loyal Customer",IF(AND(B76>=2,C76>=50000,E76<=90),"Potential Customer",IF(E76>90,"At Risk","Low Value")))) -> Low Value
